cereslib/__init__.py
cereslib/_version.py
cereslib/dfutils/__init__.py
cereslib/dfutils/filter.py
cereslib/dfutils/format.py
cereslib/enrich/__init__.py
cereslib/enrich/enrich.py
cereslib/events/__init__.py
cereslib/events/events.py
cereslib-1.1.6.dist-info/METADATA
cereslib-1.1.6.dist-info/WHEEL
cereslib-1.1.6.dist-info/licenses/AUTHORS
cereslib-1.1.6.dist-info/licenses/LICENSE
cereslib-1.1.6.dist-info/RECORD
